{
  "inputs": {
    "worker/index.ts": {
      "bytes": 2791,
      "imports": [
        {
          "path": "cloudflare:workers",
          "kind": "import-statement",
          "external": true
        },
        {
          "path": "<runtime>",
          "kind": "import-statement",
          "external": true
        }
      ],
      "format": "esm"
    }
  },
  "outputs": {
    ".alchemy/out/t2t-worker/index.js.map": {
      "imports": [],
      "exports": [],
      "inputs": {},
      "bytes": 4715
    },
    ".alchemy/out/t2t-worker/index.js": {
      "imports": [
        {
          "path": "cloudflare:workers",
          "kind": "import-statement",
          "external": true
        }
      ],
      "exports": [
        "MyDO",
        "default"
      ],
      "entryPoint": "worker/index.ts",
      "inputs": {
        "worker/index.ts": {
          "bytesInOutput": 2171
        }
      },
      "bytes": 2401
    }
  }
}